{"id":{"0":0,"1":1,"2":2,"3":3,"4":4,"5":5},"Num_pages":{"0":"835 pages","1":"Hobbit Movie Tie-in Boxed set","2":"662 pages","3":"1007 pages","4":"Reissue Edition","5":"814 pages"},"Verify_pages":{"0":["Mass Market Paperback","835 pages"],"1":["Mass Market Paperback","Hobbit Movie Tie-in Boxed set","1728 pages"],"2":["Hardcover","662 pages"],"3":["Hardcover","1007 pages"],"4":["Paperback","Reissue Edition","767 pages"],"5":["Mass Market Paperback","814 pages"]},"Awards":{"0":["Nebula Award Nominee for Best Novel (1997)","Locus Award for Best Fantasy Novel (1997)","World Fantasy Award Nominee for Best Novel (1997)","Premio Ignotus for Novela extranjera (2003)"],"1":[],"2":["Locus Award Nominee for Best First Novel and Best Fantasy Novel (2008)","Compton Crook Award Nominee (2008)","Grand Prix de l'Imaginaire Nominee for Roman \u00e9tranger and Traduction (2010)","ALA Alex Award (2008)","The Quill Award for Science Fiction\/Fantasy\/Horror (2007)","Sakura Medal for High School Book (2009)","Premio Ignotus Nominee for Mejor novela extranjera (Best Foreign Novel) (2010)","T\u00e4htifantasia Award Nominee (2011)"],"3":["Locus Award Nominee for Best Fantasy Novel (2011)","David Gemmell Legend Award for Best Fantasy Novel (2011)","Whitney Award for Best Novel (2010)","Goodreads Choice Award Nominee for Fantasy and for Favorite Book and for Goodreads Author (2010)"],"4":[],"5":["Locus Award Nominee for Best Fantasy Book (1991)"]},"Genre":{"0":["Fantasy","Fiction","Fantasy","Epic Fantasy","Adult","Science Fiction Fantasy","Fantasy","High Fantasy","Adventure","Fantasy","Dragons","Audiobook","Epic"],"1":["Fantasy","Fiction","Classics","Adventure","Science Fiction Fantasy","Fantasy","Epic Fantasy","Fantasy","High Fantasy","Young Adult","Literature","Fantasy","Magic"],"2":["Fantasy","Fiction","Fantasy","Epic Fantasy","Fantasy","High Fantasy","Fantasy","Magic","Science Fiction Fantasy","Adult","Adventure","Audiobook","Epic"],"3":["Fantasy","Fiction","Fantasy","Epic Fantasy","Fantasy","High Fantasy","Audiobook","Science Fiction Fantasy","Adult","Epic","Fantasy","Magic","Adventure"],"4":["Fantasy","Classics","Fiction","Young Adult","Childrens","Christian","Adventure","Childrens","Middle Grade","Science Fiction Fantasy","Christian Fiction"],"5":["Fantasy","Fiction","Fantasy","Epic Fantasy","Fantasy","High Fantasy","Science Fiction Fantasy","Adventure","Fantasy","Magic","Adult","Audiobook","Epic"]},"Setting":{"0":["The Lands of Ice and Fire"],"1":["Middle-earth"],"2":[],"3":["Roshar"],"4":["London, England"],"5":["Emond's Field","Caemlyn","The Blight"]},"OriginalPDate":{"0":["\n              (first published August 6th 1996)\n            "],"1":["\n              (first published October 20th 1955)\n            "],"2":["\n              (first published March 27th 2007)\n            "],"3":[],"4":["\n              (first published 1956)\n            "],"5":["\n              (first published January 15th 1990)\n            "]},"VerifyDate":{"0":[null],"1":[null],"2":[null],"3":[null],"4":[null],"5":[null]},"Series":{"0":true,"1":true,"2":true,"3":true,"4":true,"5":true},"Series-Name":{"0":"\nSeries\n\nA Song of Ice and Fire #1 \n","1":"\nSeries\n\nThe Lord of the Rings #0-3, Middle-earth Universe \n","2":"\nSeries\n\nThe Kingkiller Chronicle #1 \n","3":"\nSeries\n\nThe Stormlight Archive #1, The Cosmere \n","4":"\nSeries\n\nThe Chronicles of Narnia (Publication Order) #1\u20137, The Chronicles of Narnia (Chronological Order) #1\u20137 \n","5":"\nSeries\n\nThe Wheel of Time #1 \n"},"ISBN":{"0":"\nISBN\n\n                  0553588486\n                      (ISBN13: 9780553588484)\n\n","1":"\nISBN\n\n                  0345538374\n                      (ISBN13: 9780345538376)\n\n","2":"\nISBN\n\n                  075640407X\n                      (ISBN13: 9780756404079)\n\n","3":"\nISBN\n\n                  0765326353\n                      (ISBN13: 9780765326355)\n\n","4":"NA","5":"\nISBN\n\n                  0812511816\n                      (ISBN13: 9780812511819)\n\n"}}